fastshermanmorrison_pulsar-0.5.4.dist-info/WHEEL
fastshermanmorrison_pulsar-0.5.4.dist-info/top_level.txt
fastshermanmorrison_pulsar-0.5.4.dist-info/METADATA
fastshermanmorrison_pulsar-0.5.4.dist-info/RECORD
fastshermanmorrison_pulsar-0.5.4.dist-info/licenses/AUTHORS.md
fastshermanmorrison_pulsar-0.5.4.dist-info/licenses/LICENSE
fastshermanmorrison/cython_fastshermanmorrison.cpython-310-x86_64-linux-gnu.so
fastshermanmorrison/fastshermanmorrison.c
fastshermanmorrison/_version.py
fastshermanmorrison/fastshermanmorrison.py
fastshermanmorrison/cython_fastshermanmorrison.pyx
fastshermanmorrison/cython_fastshermanmorrison.c
fastshermanmorrison/__init__.py
