Metadata-Version: 2.4
Name: fastshermanmorrison-pulsar
Version: 0.5.4
Summary: The Enterprise add-on FastShermanMorrison for optimized EcorrKernel calculations
Home-page: http://github.com/nanograv/fastshermanmorrison/
Author: Rutger van Haasteren
Author-email: Rutger van Haasteren <rutger@vhaasteren.com>
License: MIT License
Project-URL: Homepage, https://github.com/nanograv/fastshermanmorrison
Project-URL: Bug Tracker, https://github.com/nanograv/fastshermanmorrison/issues
Classifier: Programming Language :: Python :: 3
Classifier: License :: OSI Approved :: MIT License
Classifier: Operating System :: OS Independent
Requires-Python: >=3.8
License-File: LICENSE
License-File: AUTHORS.md
Dynamic: author
Dynamic: home-page
Dynamic: license-file
